docassemble/ALMassachusetts/__init__.py
docassemble/ALMassachusetts/data/questions/al_massachusetts.yml
docassemble/ALMassachusetts/data/sources/README.md
docassemble/ALMassachusetts/data/sources/court_emails.yml
docassemble/ALMassachusetts/data/static/README.md
docassemble/ALMassachusetts/data/static/mass_icon.png
docassemble/ALMassachusetts/data/templates/README.md
docassemble/ALMassachusetts/data/templates/ma_basic_addendum.docx
docassemble_almassachusetts-0.2.0.dist-info/licenses/LICENSE
docassemble_almassachusetts-0.2.0.dist-info/METADATA
docassemble_almassachusetts-0.2.0.dist-info/WHEEL
docassemble_almassachusetts-0.2.0.dist-info/top_level.txt
docassemble_almassachusetts-0.2.0.dist-info/RECORD
