Metadata-Version: 2.4
Name: docassemble.ALMassachusetts
Version: 0.2.0
Summary: A docassemble extension of the AssemblyLine project that provides a foundation of Massachusetts-specific data, functionality, and questions.
Home-page: https://suffolklitlab.org/docassemble-AssemblyLine-documentation/docs
Author: AssemblyLine Team
Author-email: litlab@suffolk.org
License: The MIT License (MIT)
License-File: LICENSE
Requires-Dist: docassemble.MACourts>=1.2.0
Dynamic: author
Dynamic: author-email
Dynamic: description
Dynamic: description-content-type
Dynamic: home-page
Dynamic: license
Dynamic: license-file
Dynamic: requires-dist
Dynamic: summary
